[
  {
    "typeId" : "propertyType",
    "tid": "votePredRstrtn",
    "id": "votePredRstrtn@vodSeq",
    "pid": "vodSeq",
    "propertyTypeName": "투표 일련번호",
    "valueType": "INT",
    "required": true,
    "idable": true,
    "labelable": false,
    "treeable": false,
    "indexable": true,
    "analyzer": null,
    "referenceType": "",
    "referenceValue": ""
  },
  {
    "typeId" : "propertyType",
    "tid": "votePredRstrtn",
    "id": "votePredRstrtn@rstrtnPredStDt",
    "pid": "rstrtnPredStDt",
    "propertyTypeName": "제한기간 시작일시",
    "valueType": "DATE",
    "required": false,
    "idable": false,
    "labelable": false,
    "treeable": false,
    "indexable": false,
    "analyzer": null,
    "referenceType": "",
    "referenceValue": ""
  },
  {
    "typeId": "propertyType",
    "tid": "votePredRstrtn",
    "id": "votePredRstrtn@rstrtnPredFnsDt",
    "pid": "rstrtnPredFnsDt",
    "propertyTypeName": "제한기간 종료일시",
    "valueType": "DATE",
    "required": false,
    "idable": false,
    "labelable": false,
    "treeable": false,
    "indexable": false,
    "analyzer": null,
    "referenceType": "",
    "referenceValue": ""
  },
  {
    "typeId" : "propertyType",
    "tid": "votePredRstrtn",
    "id": "votePredRstrtn@voteCnt",
    "pid": "voteCnt",
    "propertyTypeName": "투표수",
    "valueType": "INT",
    "required": false,
    "idable": false,
    "labelable": false,
    "treeable": false,
    "indexable": false,
    "analyzer": null,
    "referenceType": "",
    "referenceValue": ""
  }
]