[
  {
    "parentId" : "mbrMng",
    "typeId" : "nodeType",
    "id" : "mbrInfo",
    "tid" : "mbrInfo",
    "typeName" : "회원 정보",
    "repositoryType" : "node",
    "tableName": "cjDb#mbrInfo",
    "eviction" : 100
  },
  {
    "parentId" : "mbrMng",
    "typeId" : "nodeType",
    "id" : "mbrDvcInfo",
    "tid" : "mbrDvcInfo",
    "typeName" : "회원 디바이스 정보",
    "repositoryType" : "node",
    "tableName": "cjDb#mbrDvcInfo",
    "eviction" : 100
  },
  {
    "parentId" : "mbrMng",
    "typeId" : "nodeType",
    "id" : "mbrSttusInfoHist",
    "tid" : "mbrSttusInfoHist",
    "typeName" : "회원 상태정보 이력",
    "repositoryType" : "node",
    "tableName": "cjDb#mbrSttusInfoHist",
    "eviction" : 100
  },
  {
    "parentId" : "mbrMng",
    "typeId" : "nodeType",
    "id" : "mbrBlackListHist",
    "tid" : "mbrBlackListHist",
    "typeName" : "회원 블랙리스트 이력",
    "repositoryType" : "node",
    "tableName": "cjDb#mbrBlackListHist",
    "eviction" : 100
  },
  {
    "parentId" : "mbrMng",
    "typeId" : "nodeType",
    "id" : "mbrDclarList",
    "tid" : "mbrDclarList",
    "typeName" : "블랙리스트 신고 목록",
    "repositoryType" : "node",
    "tableName": "cjDb#mbrDclarList",
    "eviction" : 100
  },
  {
    "parentId" : "mbrMng",
    "typeId" : "nodeType",
    "id" : "blackListDclarMng",
    "tid" : "blackListDclarMng",
    "typeName" : "블랙리스트 신고 설정관리",
    "repositoryType" : "node",
    "tableName": "cjDb#blackListDclarMng",
    "eviction" : 100
  },
  {
    "parentId" : "mbrMng",
    "typeId" : "nodeType",
    "id" : "nosubsMbrInfo",
    "tid" : "nosubsMbrInfo",
    "typeName" : "비회원 정보",
    "repositoryType" : "node",
    "tableName": "cjDb#nosubsMbrInfo",
    "eviction" : 100
  }
]