[
  {
    "typeId": "propertyTypeValidation",
    "id": "propertyTypeValidation>evPwnrInfo>evPwnrSeq",
    "propertyTypeId": "evPwnrInfo>evPwnrSeq",
    "validation": {
      "language": "ko",
      "required": {
        "value": true,
        "description": "필수 값 입니다."
      },
      "duplicated": {
        "value": true,
        "description": "중복된 값 입니다."
      },
      "min": {
        "value": 0,
        "description": "최소 값 입니다."
      },
      "max": {
        "value": 0,
        "description": "최대 값 입니다."
      },
      "extention": {
        "value": "",
        "description": "확장자를 허용하지 않습니다."
      },
      "regularExpression": {
        "value": "",
        "description": ""
      }
    }
  },
  {
    "typeId": "propertyTypeValidation",
    "id": "propertyTypeValidation>evPwnrInfo>eventNm",
    "propertyTypeId": "evPwnrInfo>eventNm",
    "validation": {
      "language": "ko",
      "required": {
        "value": true,
        "description": "필수 값 입니다."
      },
      "duplicated": {
        "value": false,
        "description": "중복된 값 입니다."
      },
      "min": {
        "value": 0,
        "description": "최소 값 입니다."
      },
      "max": {
        "value": 0,
        "description": "최대 값 입니다."
      },
      "extention": {
        "value": "",
        "description": "확장자를 허용하지 않습니다."
      },
      "regularExpression": {
        "value": "",
        "description": ""
      }
    }
  },
  {
    "typeId": "propertyTypeValidation",
    "id": "propertyTypeValidation>evPwnrInfo>mbrId",
    "propertyTypeId": "evPwnrInfo>mbrId",
    "validation": {
      "language": "ko",
      "required": {
        "value": true,
        "description": "필수 값 입니다."
      },
      "duplicated": {
        "value": false,
        "description": "중복된 값 입니다."
      },
      "min": {
        "value": 0,
        "description": "최소 값 입니다."
      },
      "max": {
        "value": 0,
        "description": "최대 값 입니다."
      },
      "extention": {
        "value": "",
        "description": "확장자를 허용하지 않습니다."
      },
      "regularExpression": {
        "value": "",
        "description": ""
      }
    }
  },
  {
    "typeId": "propertyTypeValidation",
    "id": "propertyTypeValidation>evPwnrInfo>mbrName",
    "propertyTypeId": "evPwnrInfo>mbrName",
    "validation": {
      "language": "ko",
      "required": {
        "value": true,
        "description": "필수 값 입니다."
      },
      "duplicated": {
        "value": false,
        "description": "중복된 값 입니다."
      },
      "min": {
        "value": 0,
        "description": "최소 값 입니다."
      },
      "max": {
        "value": 0,
        "description": "최대 값 입니다."
      },
      "extention": {
        "value": "",
        "description": "확장자를 허용하지 않습니다."
      },
      "regularExpression": {
        "value": "",
        "description": ""
      }
    }
  },
  {
    "typeId": "propertyTypeValidation",
    "id": "propertyTypeValidation>evPwnrInfo>email",
    "propertyTypeId": "evPwnrInfo>email",
    "validation": {
      "language": "ko",
      "required": {
        "value": false,
        "description": "필수 값 입니다."
      },
      "duplicated": {
        "value": false,
        "description": "중복된 값 입니다."
      },
      "min": {
        "value": 0,
        "description": "최소 값 입니다."
      },
      "max": {
        "value": 0,
        "description": "최대 값 입니다."
      },
      "extention": {
        "value": "",
        "description": "확장자를 허용하지 않습니다."
      },
      "regularExpression": {
        "value": "",
        "description": ""
      }
    }
  },
  {
    "typeId": "propertyTypeValidation",
    "id": "propertyTypeValidation>evPwnrInfo>mblNo",
    "propertyTypeId": "evPwnrInfo>mblNo",
    "validation": {
      "language": "ko",
      "required": {
        "value": true,
        "description": "필수 값 입니다."
      },
      "duplicated": {
        "value": false,
        "description": "중복된 값 입니다."
      },
      "min": {
        "value": 0,
        "description": "최소 값 입니다."
      },
      "max": {
        "value": 0,
        "description": "최대 값 입니다."
      },
      "extention": {
        "value": "",
        "description": "확장자를 허용하지 않습니다."
      },
      "regularExpression": {
        "value": "",
        "description": ""
      }
    }
  },
  {
    "typeId": "propertyTypeValidation",
    "id": "propertyTypeValidation>evPwnrInfo>homeZipCode",
    "propertyTypeId": "evPwnrInfo>homeZipCode",
    "validation": {
      "language": "ko",
      "required": {
        "value": false,
        "description": "필수 값 입니다."
      },
      "duplicated": {
        "value": false,
        "description": "중복된 값 입니다."
      },
      "min": {
        "value": 0,
        "description": "최소 값 입니다."
      },
      "max": {
        "value": 0,
        "description": "최대 값 입니다."
      },
      "extention": {
        "value": "",
        "description": "확장자를 허용하지 않습니다."
      },
      "regularExpression": {
        "value": "",
        "description": ""
      }
    }
  },
  {
    "typeId": "propertyTypeValidation",
    "id": "propertyTypeValidation>evPwnrInfo>homeAdr1",
    "propertyTypeId": "evPwnrInfo>homeAdr1",
    "validation": {
      "language": "ko",
      "required": {
        "value": false,
        "description": "필수 값 입니다."
      },
      "duplicated": {
        "value": false,
        "description": "중복된 값 입니다."
      },
      "min": {
        "value": 0,
        "description": "최소 값 입니다."
      },
      "max": {
        "value": 0,
        "description": "최대 값 입니다."
      },
      "extention": {
        "value": "",
        "description": "확장자를 허용하지 않습니다."
      },
      "regularExpression": {
        "value": "",
        "description": ""
      }
    }
  },
  {
    "typeId": "propertyTypeValidation",
    "id": "propertyTypeValidation>evPwnrInfo>homeAdr2",
    "propertyTypeId": "evPwnrInfo>homeAdr2",
    "validation": {
      "language": "ko",
      "required": {
        "value": false,
        "description": "필수 값 입니다."
      },
      "duplicated": {
        "value": false,
        "description": "중복된 값 입니다."
      },
      "min": {
        "value": 0,
        "description": "최소 값 입니다."
      },
      "max": {
        "value": 0,
        "description": "최대 값 입니다."
      },
      "extention": {
        "value": "",
        "description": "확장자를 허용하지 않습니다."
      },
      "regularExpression": {
        "value": "",
        "description": ""
      }
    }
  },
  {
    "typeId": "propertyTypeValidation",
    "id": "propertyTypeValidation>evPwnrInfo>memo",
    "propertyTypeId": "evPwnrInfo>memo",
    "validation": {
      "language": "ko",
      "required": {
        "value": false,
        "description": "필수 값 입니다."
      },
      "duplicated": {
        "value": false,
        "description": "중복된 값 입니다."
      },
      "min": {
        "value": 0,
        "description": "최소 값 입니다."
      },
      "max": {
        "value": 0,
        "description": "최대 값 입니다."
      },
      "extention": {
        "value": "",
        "description": "확장자를 허용하지 않습니다."
      },
      "regularExpression": {
        "value": "",
        "description": ""
      }
    }
  },
  {
    "typeId": "propertyTypeValidation",
    "id": "propertyTypeValidation>evPwnrInfo>indvInfoAgreeYn",
    "propertyTypeId": "evPwnrInfo>indvInfoAgreeYn",
    "validation": {
      "language": "ko",
      "required": {
        "value": true,
        "description": "필수 값 입니다."
      },
      "duplicated": {
        "value": false,
        "description": "중복된 값 입니다."
      },
      "min": {
        "value": 0,
        "description": "최소 값 입니다."
      },
      "max": {
        "value": 0,
        "description": "최대 값 입니다."
      },
      "extention": {
        "value": "",
        "description": "확장자를 허용하지 않습니다."
      },
      "regularExpression": {
        "value": "",
        "description": ""
      }
    }
  },
  {
    "typeId": "propertyTypeValidation",
    "id": "propertyTypeValidation>evPwnrInfo>selItemAgreeYn",
    "propertyTypeId": "evPwnrInfo>selItemAgreeYn",
    "validation": {
      "language": "ko",
      "required": {
        "value": true,
        "description": "필수 값 입니다."
      },
      "duplicated": {
        "value": false,
        "description": "중복된 값 입니다."
      },
      "min": {
        "value": 0,
        "description": "최소 값 입니다."
      },
      "max": {
        "value": 0,
        "description": "최대 값 입니다."
      },
      "extention": {
        "value": "",
        "description": "확장자를 허용하지 않습니다."
      },
      "regularExpression": {
        "value": "",
        "description": ""
      }
    }
  },
  {
    "typeId": "propertyTypeValidation",
    "id": "propertyTypeValidation>evPwnrInfo>owner",
    "propertyTypeId": "evPwnrInfo>owner",
    "validation": {
      "language": "ko",
      "required": {
        "value": false,
        "description": "필수 값 입니다."
      },
      "duplicated": {
        "value": false,
        "description": "중복된 값 입니다."
      },
      "min": {
        "value": 0,
        "description": "최소 값 입니다."
      },
      "max": {
        "value": 0,
        "description": "최대 값 입니다."
      },
      "extention": {
        "value": "",
        "description": "확장자를 허용하지 않습니다."
      },
      "regularExpression": {
        "value": "",
        "description": ""
      }
    }
  },
  {
    "typeId": "propertyTypeValidation",
    "id": "propertyTypeValidation>evPwnrInfo>created",
    "propertyTypeId": "evPwnrInfo>created",
    "validation": {
      "language": "ko",
      "required": {
        "value": false,
        "description": "필수 값 입니다."
      },
      "duplicated": {
        "value": false,
        "description": "중복된 값 입니다."
      },
      "min": {
        "value": 0,
        "description": "최소 값 입니다."
      },
      "max": {
        "value": 0,
        "description": "최대 값 입니다."
      },
      "extention": {
        "value": "",
        "description": "확장자를 허용하지 않습니다."
      },
      "regularExpression": {
        "value": "",
        "description": ""
      }
    }
  },
  {
    "typeId": "propertyTypeValidation",
    "id": "propertyTypeValidation>evPwnrInfo>modifier",
    "propertyTypeId": "evPwnrInfo>modifier",
    "validation": {
      "language": "ko",
      "required": {
        "value": false,
        "description": "필수 값 입니다."
      },
      "duplicated": {
        "value": false,
        "description": "중복된 값 입니다."
      },
      "min": {
        "value": 0,
        "description": "최소 값 입니다."
      },
      "max": {
        "value": 0,
        "description": "최대 값 입니다."
      },
      "extention": {
        "value": "",
        "description": "확장자를 허용하지 않습니다."
      },
      "regularExpression": {
        "value": "",
        "description": ""
      }
    }
  },
  {
    "typeId": "propertyTypeValidation",
    "id": "propertyTypeValidation>evPwnrInfo>changed",
    "propertyTypeId": "evPwnrInfo>changed",
    "validation": {
      "language": "ko",
      "required": {
        "value": false,
        "description": "필수 값 입니다."
      },
      "duplicated": {
        "value": false,
        "description": "중복된 값 입니다."
      },
      "min": {
        "value": 0,
        "description": "최소 값 입니다."
      },
      "max": {
        "value": 0,
        "description": "최대 값 입니다."
      },
      "extention": {
        "value": "",
        "description": "확장자를 허용하지 않습니다."
      },
      "regularExpression": {
        "value": "",
        "description": ""
      }
    }
  }
]