[
  {
    "typeId": "news",
    "newsId": "112724",
    "newsNm": "법무부 감찰관·법무심의관도 '탈검찰화'…개혁위 첫 권고",
    "ctgryId": "5567",
    "authrName": "고동욱",
    "newsDesc": "검찰 개혁의 주요 과제 중 하나로 추진되는 '법무부 탈검찰화'가 주요 실·국장 외의 보직으로 확대된다. 법무부는 24일 법무·검찰개혁위원회(위원장 한인섭)가 법무부 탈검찰화와 관련해 직제 개정과 인사 방향 등을 담은 첫 권고안을 발표했다고 밝혔다. 권고 내용은 직제 개정, 법무부 실·국장 및 과장급 인사, 평검사 인사와 관련한 구체적인 내용이 담겼다.위원회는 현재 검사만 보임하게 돼 있는 감찰관과 법무심의관 직위를 일반직공무원에 개방하도록 직제를 개정하라고 권고했다.",
    "mscomName": "yna",
    "thumImgPath": "",
    "showTitle": "법무부 감찰관·법무심의관도 '탈검찰화'…개혁위 첫 권고",
    "apvSttusCd": "1",
    "artclOriginUrl": "http://news.naver.com/main/hotissue/read.nhn?mid=hot&sid1=101&cid=1068697&iid=5048564&oid=001&aid=0009495135&ptype=052",
    "refNewsIds": "",
    "relArtistIds": "",
    "relSongIds": "",
    "refVodIds": "",
    "refClipIds": "",
    "findKywrd": "법무부",
    "langCd": "KOR"
  }
]