[
  {
    "typeId" : "event",
    "tid": "pgmVideo",
    "event" : "saveMetadata",
    "eventName" : "Save metadata"
  },
  {
    "typeId" : "eventAction",
    "event": "pgmVideo>saveMetadata",
    "action" : "saveMetadata",
    "actionType" : "service",
    "actionBody" : "metadataService.saveMetadata",
    "order" : 1
  },
  {
    "typeId": "event",
    "tid": "pgmVideo",
    "event": "getUrl",
    "noneExecute" : true,
    "eventName": "CDN URL Event"
  },
  {
    "typeId": "eventAction",
    "event": "pgmVideo>getUrl",
    "action": "getUrlEvent",
    "actionName": "PIP CDN URL 변환",
    "actionType": "service",
    "actionBody": "videoService.getVideoCdnUrl",
    "order": 1
  },
  {
    "typeId": "event",
    "tid": "pgmVideo",
    "event": "view",
    "noneExecute": true,
    "eventName": "hitNum Event"
  },
  {
    "typeId": "eventAction",
    "event": "pgmVideo>view",
    "action": "hitNumUpdEvent",
    "actionName": "pgmVideo 조회수 업데이트",
    "actionType": "service",
    "actionBody": "contsRetvService.hitNumUpdate",
    "order": 1
  },
  {
    "typeId": "eventListener",
    "tid": "contsRetvHst",
    "event": "pgmVideo>view",
    "listenerName": "pgmVideo 조회시 콘텐츠 조회 create",
    "actionType": "service",
    "actionBody": "contsRetvService.insert"
  }
]