[
  {
    "typeId": "propertyTypeValidation",
    "id": "propertyTypeValidation>compItemInfo>compItemSeq",
    "propertyTypeId": "compItemInfo>compItemSeq",
    "validation": {
      "language": "ko",
      "required": {
        "value": true,
        "description": "필수 값 입니다."
      },
      "duplicated": {
        "value": true,
        "description": "중복된 값 입니다."
      },
      "min": {
        "value": 0,
        "description": "최소 값 입니다."
      },
      "max": {
        "value": 0,
        "description": "최대 값 입니다."
      },
      "extention": {
        "value": "",
        "description": "확장자를 허용하지 않습니다."
      },
      "regularExpression": {
        "value": "",
        "description": ""
      }
    }
  },
  {
    "typeId": "propertyTypeValidation",
    "id": "propertyTypeValidation>compItemInfo>mainSeq",
    "propertyTypeId": "compItemInfo>mainSeq",
    "validation": {
      "language": "ko",
      "required": {
        "value": true,
        "description": "필수 값 입니다."
      },
      "duplicated": {
        "value": false,
        "description": "중복된 값 입니다."
      },
      "min": {
        "value": 0,
        "description": "최소 값 입니다."
      },
      "max": {
        "value": 0,
        "description": "최대 값 입니다."
      },
      "extention": {
        "value": "",
        "description": "확장자를 허용하지 않습니다."
      },
      "regularExpression": {
        "value": "",
        "description": ""
      }
    }
  },
  {
    "typeId": "propertyTypeValidation",
    "id": "propertyTypeValidation>compItemInfo>itemDivCd",
    "propertyTypeId": "compItemInfo>itemDivCd",
    "validation": {
      "language": "ko",
      "required": {
        "value": true,
        "description": "필수 값 입니다."
      },
      "duplicated": {
        "value": false,
        "description": "중복된 값 입니다."
      },
      "min": {
        "value": 0,
        "description": "최소 값 입니다."
      },
      "max": {
        "value": 0,
        "description": "최대 값 입니다."
      },
      "extention": {
        "value": "",
        "description": "확장자를 허용하지 않습니다."
      },
      "regularExpression": {
        "value": "",
        "description": ""
      }
    }
  },
  {
    "typeId": "propertyTypeValidation",
    "id": "propertyTypeValidation>compItemInfo>itemId",
    "propertyTypeId": "compItemInfo>itemId",
    "validation": {
      "language": "ko",
      "required": {
        "value": false,
        "description": "필수 값 입니다."
      },
      "duplicated": {
        "value": false,
        "description": "중복된 값 입니다."
      },
      "min": {
        "value": 0,
        "description": "최소 값 입니다."
      },
      "max": {
        "value": 0,
        "description": "최대 값 입니다."
      },
      "extention": {
        "value": "",
        "description": "확장자를 허용하지 않습니다."
      },
      "regularExpression": {
        "value": "",
        "description": ""
      }
    }
  },
  {
    "typeId": "propertyTypeValidation",
    "id": "propertyTypeValidation>compItemInfo>itemNm",
    "propertyTypeId": "compItemInfo>itemNm",
    "validation": {
      "language": "ko",
      "required": {
        "value": true,
        "description": "필수 값 입니다."
      },
      "duplicated": {
        "value": false,
        "description": "중복된 값 입니다."
      },
      "min": {
        "value": 0,
        "description": "최소 값 입니다."
      },
      "max": {
        "value": 0,
        "description": "최대 값 입니다."
      },
      "extention": {
        "value": "",
        "description": "확장자를 허용하지 않습니다."
      },
      "regularExpression": {
        "value": "",
        "description": ""
      }
    }
  },
  {
    "typeId": "propertyTypeValidation",
    "id": "propertyTypeValidation>compItemInfo>subName",
    "propertyTypeId": "compItemInfo>subName",
    "validation": {
      "language": "ko",
      "required": {
        "value": false,
        "description": "필수 값 입니다."
      },
      "duplicated": {
        "value": false,
        "description": "중복된 값 입니다."
      },
      "min": {
        "value": 0,
        "description": "최소 값 입니다."
      },
      "max": {
        "value": 0,
        "description": "최대 값 입니다."
      },
      "extention": {
        "value": "",
        "description": "확장자를 허용하지 않습니다."
      },
      "regularExpression": {
        "value": "",
        "description": ""
      }
    }
  },
  {
    "typeId": "propertyTypeValidation",
    "id": "propertyTypeValidation>compItemInfo>typeCd",
    "propertyTypeId": "compItemInfo>typeCd",
    "validation": {
      "language": "ko",
      "required": {
        "value": true,
        "description": "필수 값 입니다."
      },
      "duplicated": {
        "value": false,
        "description": "중복된 값 입니다."
      },
      "min": {
        "value": 0,
        "description": "최소 값 입니다."
      },
      "max": {
        "value": 0,
        "description": "최대 값 입니다."
      },
      "extention": {
        "value": "",
        "description": "확장자를 허용하지 않습니다."
      },
      "regularExpression": {
        "value": "",
        "description": ""
      }
    }
  },
  {
    "typeId": "propertyTypeValidation",
    "id": "propertyTypeValidation>compItemInfo>ifTgtCd",
    "propertyTypeId": "compItemInfo>ifTgtCd",
    "validation": {
      "language": "ko",
      "required": {
        "value": false,
        "description": "필수 값 입니다."
      },
      "duplicated": {
        "value": false,
        "description": "중복된 값 입니다."
      },
      "min": {
        "value": 0,
        "description": "최소 값 입니다."
      },
      "max": {
        "value": 0,
        "description": "최대 값 입니다."
      },
      "extention": {
        "value": "",
        "description": "확장자를 허용하지 않습니다."
      },
      "regularExpression": {
        "value": "",
        "description": ""
      }
    }
  },
  {
    "typeId": "propertyTypeValidation",
    "id": "propertyTypeValidation>compItemInfo>showYn",
    "propertyTypeId": "compItemInfo>showYn",
    "validation": {
      "language": "ko",
      "required": {
        "value": true,
        "description": "필수 값 입니다."
      },
      "duplicated": {
        "value": false,
        "description": "중복된 값 입니다."
      },
      "min": {
        "value": 0,
        "description": "최소 값 입니다."
      },
      "max": {
        "value": 0,
        "description": "최대 값 입니다."
      },
      "extention": {
        "value": "",
        "description": "확장자를 허용하지 않습니다."
      },
      "regularExpression": {
        "value": "",
        "description": ""
      }
    }
  },
  {
    "typeId": "propertyTypeValidation",
    "id": "propertyTypeValidation>compItemInfo>sortOdrg",
    "propertyTypeId": "compItemInfo>sortOdrg",
    "validation": {
      "language": "ko",
      "required": {
        "value": false,
        "description": "필수 값 입니다."
      },
      "duplicated": {
        "value": false,
        "description": "중복된 값 입니다."
      },
      "min": {
        "value": 0,
        "description": "최소 값 입니다."
      },
      "max": {
        "value": 0,
        "description": "최대 값 입니다."
      },
      "extention": {
        "value": "",
        "description": "확장자를 허용하지 않습니다."
      },
      "regularExpression": {
        "value": "",
        "description": ""
      }
    }
  },
  {
    "typeId": "propertyTypeValidation",
    "id": "propertyTypeValidation>compItemInfo>showCntryCdList",
    "propertyTypeId": "compItemInfo>showCntryCdList",
    "validation": {
      "language": "ko",
      "required": {
        "value": true,
        "description": "필수 값 입니다."
      },
      "duplicated": {
        "value": false,
        "description": "중복된 값 입니다."
      },
      "min": {
        "value": 0,
        "description": "최소 값 입니다."
      },
      "max": {
        "value": 0,
        "description": "최대 값 입니다."
      },
      "extention": {
        "value": "",
        "description": "확장자를 허용하지 않습니다."
      },
      "regularExpression": {
        "value": "",
        "description": ""
      }
    }
  },
  {
    "typeId": "propertyTypeValidation",
    "id": "propertyTypeValidation>compItemInfo>bgOptnYn",
    "propertyTypeId": "compItemInfo>bgOptnYn",
    "validation": {
      "language": "ko",
      "required": {
        "value": false,
        "description": "필수 값 입니다."
      },
      "duplicated": {
        "value": false,
        "description": "중복된 값 입니다."
      },
      "min": {
        "value": 0,
        "description": "최소 값 입니다."
      },
      "max": {
        "value": 0,
        "description": "최대 값 입니다."
      },
      "extention": {
        "value": "",
        "description": "확장자를 허용하지 않습니다."
      },
      "regularExpression": {
        "value": "",
        "description": ""
      }
    }
  },
  {
    "typeId": "propertyTypeValidation",
    "id": "propertyTypeValidation>compItemInfo>cnctContsDivCd",
    "propertyTypeId": "compItemInfo>cnctContsDivCd",
    "validation": {
      "language": "ko",
      "required": {
        "value": false,
        "description": "필수 값 입니다."
      },
      "duplicated": {
        "value": false,
        "description": "중복된 값 입니다."
      },
      "min": {
        "value": 0,
        "description": "최소 값 입니다."
      },
      "max": {
        "value": 0,
        "description": "최대 값 입니다."
      },
      "extention": {
        "value": "",
        "description": "확장자를 허용하지 않습니다."
      },
      "regularExpression": {
        "value": "",
        "description": ""
      }
    }
  },
  {
    "typeId": "propertyTypeValidation",
    "id": "propertyTypeValidation>compItemInfo>cnctContsNm",
    "propertyTypeId": "compItemInfo>cnctContsNm",
    "validation": {
      "language": "ko",
      "required": {
        "value": false,
        "description": "필수 값 입니다."
      },
      "duplicated": {
        "value": false,
        "description": "중복된 값 입니다."
      },
      "min": {
        "value": 0,
        "description": "최소 값 입니다."
      },
      "max": {
        "value": 0,
        "description": "최대 값 입니다."
      },
      "extention": {
        "value": "",
        "description": "확장자를 허용하지 않습니다."
      },
      "regularExpression": {
        "value": "",
        "description": ""
      }
    }
  },
  {
    "typeId": "propertyTypeValidation",
    "id": "propertyTypeValidation>compItemInfo>cnctContsIfTgtCd",
    "propertyTypeId": "compItemInfo>cnctContsIfTgtCd",
    "validation": {
      "language": "ko",
      "required": {
        "value": false,
        "description": "필수 값 입니다."
      },
      "duplicated": {
        "value": false,
        "description": "중복된 값 입니다."
      },
      "min": {
        "value": 0,
        "description": "최소 값 입니다."
      },
      "max": {
        "value": 0,
        "description": "최대 값 입니다."
      },
      "extention": {
        "value": "",
        "description": "확장자를 허용하지 않습니다."
      },
      "regularExpression": {
        "value": "",
        "description": ""
      }
    }
  },
  {
    "typeId": "propertyTypeValidation",
    "id": "propertyTypeValidation>compItemInfo>cnctContsSortBaseCd",
    "propertyTypeId": "compItemInfo>cnctContsSortBaseCd",
    "validation": {
      "language": "ko",
      "required": {
        "value": false,
        "description": "필수 값 입니다."
      },
      "duplicated": {
        "value": false,
        "description": "중복된 값 입니다."
      },
      "min": {
        "value": 0,
        "description": "최소 값 입니다."
      },
      "max": {
        "value": 0,
        "description": "최대 값 입니다."
      },
      "extention": {
        "value": "",
        "description": "확장자를 허용하지 않습니다."
      },
      "regularExpression": {
        "value": "",
        "description": ""
      }
    }
  },
  {
    "typeId": "propertyTypeValidation",
    "id": "propertyTypeValidation>compItemInfo>cnctContsTypeCd",
    "propertyTypeId": "compItemInfo>cnctContsTypeCd",
    "validation": {
      "language": "ko",
      "required": {
        "value": false,
        "description": "필수 값 입니다."
      },
      "duplicated": {
        "value": false,
        "description": "중복된 값 입니다."
      },
      "min": {
        "value": 0,
        "description": "최소 값 입니다."
      },
      "max": {
        "value": 0,
        "description": "최대 값 입니다."
      },
      "extention": {
        "value": "",
        "description": "확장자를 허용하지 않습니다."
      },
      "regularExpression": {
        "value": "",
        "description": ""
      }
    }
  },
  {
    "typeId": "propertyTypeValidation",
    "id": "propertyTypeValidation>compItemInfo>cnctContsLeftYn",
    "propertyTypeId": "compItemInfo>cnctContsLeftYn",
    "validation": {
      "language": "ko",
      "required": {
        "value": false,
        "description": "필수 값 입니다."
      },
      "duplicated": {
        "value": false,
        "description": "중복된 값 입니다."
      },
      "min": {
        "value": 0,
        "description": "최소 값 입니다."
      },
      "max": {
        "value": 0,
        "description": "최대 값 입니다."
      },
      "extention": {
        "value": "",
        "description": "확장자를 허용하지 않습니다."
      },
      "regularExpression": {
        "value": "",
        "description": ""
      }
    }
  },
  {
    "typeId": "propertyTypeValidation",
    "id": "propertyTypeValidation>compItemInfo>cnctContsshowCntryCdList",
    "propertyTypeId": "compItemInfo>cnctContsshowCntryCdList",
    "validation": {
      "language": "ko",
      "required": {
        "value": false,
        "description": "필수 값 입니다."
      },
      "duplicated": {
        "value": false,
        "description": "중복된 값 입니다."
      },
      "min": {
        "value": 0,
        "description": "최소 값 입니다."
      },
      "max": {
        "value": 0,
        "description": "최대 값 입니다."
      },
      "extention": {
        "value": "",
        "description": "확장자를 허용하지 않습니다."
      },
      "regularExpression": {
        "value": "",
        "description": ""
      }
    }
  },
  {
    "typeId": "propertyTypeValidation",
    "id": "propertyTypeValidation>compItemInfo>cnctContsId",
    "propertyTypeId": "compItemInfo>cnctContsId",
    "validation": {
      "language": "ko",
      "required": {
        "value": false,
        "description": "필수 값 입니다."
      },
      "duplicated": {
        "value": false,
        "description": "중복된 값 입니다."
      },
      "min": {
        "value": 0,
        "description": "최소 값 입니다."
      },
      "max": {
        "value": 0,
        "description": "최대 값 입니다."
      },
      "extention": {
        "value": "",
        "description": "확장자를 허용하지 않습니다."
      },
      "regularExpression": {
        "value": "",
        "description": ""
      }
    }
  },
  {
    "typeId": "propertyTypeValidation",
    "id": "propertyTypeValidation>compItemInfo>cnctBgOptnYn",
    "propertyTypeId": "compItemInfo>cnctBgOptnYn",
    "validation": {
      "language": "ko",
      "required": {
        "value": false,
        "description": "필수 값 입니다."
      },
      "duplicated": {
        "value": false,
        "description": "중복된 값 입니다."
      },
      "min": {
        "value": 0,
        "description": "최소 값 입니다."
      },
      "max": {
        "value": 0,
        "description": "최대 값 입니다."
      },
      "extention": {
        "value": "",
        "description": "확장자를 허용하지 않습니다."
      },
      "regularExpression": {
        "value": "",
        "description": ""
      }
    }
  },
  {
    "typeId": "propertyTypeValidation",
    "id": "propertyTypeValidation>compItemInfo>refdAtribList",
    "propertyTypeId": "compItemInfo>refdAtribList",
    "validation": {
      "language": "ko",
      "required": {
        "value": false,
        "description": "필수 값 입니다."
      },
      "duplicated": {
        "value": false,
        "description": "중복된 값 입니다."
      },
      "min": {
        "value": 0,
        "description": "최소 값 입니다."
      },
      "max": {
        "value": 0,
        "description": "최대 값 입니다."
      },
      "extention": {
        "value": "",
        "description": "확장자를 허용하지 않습니다."
      },
      "regularExpression": {
        "value": "",
        "description": ""
      }
    }
  },
  {
    "typeId": "propertyTypeValidation",
    "id": "propertyTypeValidation>compItemInfo>owner",
    "propertyTypeId": "compItemInfo>owner",
    "validation": {
      "language": "ko",
      "required": {
        "value": false,
        "description": "필수 값 입니다."
      },
      "duplicated": {
        "value": false,
        "description": "중복된 값 입니다."
      },
      "min": {
        "value": 0,
        "description": "최소 값 입니다."
      },
      "max": {
        "value": 0,
        "description": "최대 값 입니다."
      },
      "extention": {
        "value": "",
        "description": "확장자를 허용하지 않습니다."
      },
      "regularExpression": {
        "value": "",
        "description": ""
      }
    }
  },
  {
    "typeId": "propertyTypeValidation",
    "id": "propertyTypeValidation>compItemInfo>created",
    "propertyTypeId": "compItemInfo>created",
    "validation": {
      "language": "ko",
      "required": {
        "value": false,
        "description": "필수 값 입니다."
      },
      "duplicated": {
        "value": false,
        "description": "중복된 값 입니다."
      },
      "min": {
        "value": 0,
        "description": "최소 값 입니다."
      },
      "max": {
        "value": 0,
        "description": "최대 값 입니다."
      },
      "extention": {
        "value": "",
        "description": "확장자를 허용하지 않습니다."
      },
      "regularExpression": {
        "value": "",
        "description": ""
      }
    }
  },
  {
    "typeId": "propertyTypeValidation",
    "id": "propertyTypeValidation>compItemInfo>modifier",
    "propertyTypeId": "compItemInfo>modifier",
    "validation": {
      "language": "ko",
      "required": {
        "value": false,
        "description": "필수 값 입니다."
      },
      "duplicated": {
        "value": false,
        "description": "중복된 값 입니다."
      },
      "min": {
        "value": 0,
        "description": "최소 값 입니다."
      },
      "max": {
        "value": 0,
        "description": "최대 값 입니다."
      },
      "extention": {
        "value": "",
        "description": "확장자를 허용하지 않습니다."
      },
      "regularExpression": {
        "value": "",
        "description": ""
      }
    }
  },
  {
    "typeId": "propertyTypeValidation",
    "id": "propertyTypeValidation>compItemInfo>changed",
    "propertyTypeId": "compItemInfo>changed",
    "validation": {
      "language": "ko",
      "required": {
        "value": false,
        "description": "필수 값 입니다."
      },
      "duplicated": {
        "value": false,
        "description": "중복된 값 입니다."
      },
      "min": {
        "value": 0,
        "description": "최소 값 입니다."
      },
      "max": {
        "value": 0,
        "description": "최대 값 입니다."
      },
      "extention": {
        "value": "",
        "description": "확장자를 허용하지 않습니다."
      },
      "regularExpression": {
        "value": "",
        "description": ""
      }
    }
  }
]