[
  {
    "typeId" : "event",
    "id" : "oneToOneQuestion>create",
    "tid": "oneToOneQuestion",
    "event" : "create",
    "eventName" : "Create OneToOneQuestion"
  },
  {
    "typeId" : "event",
    "id" : "oneToOneQuestion>update",
    "tid": "oneToOneQuestion",
    "event" : "update",
    "eventName" : "update OneToOneQuestion"
  },
  {
    "typeId" : "event",
    "id" : "oneToOneQuestion>delete",
    "tid": "oneToOneQuestion",
    "event" : "delete",
    "eventName" : "delete OneToOneQuestion"
  },
  {
    "typeId" : "event",
    "id" : "oneToOneAnswer>create",
    "tid": "oneToOneAnswer",
    "event" : "create",
    "eventName" : "Create OneToOneAnswer"
  },
  {
    "typeId" : "event",
    "id" : "oneToOneAnswer>update",
    "tid": "oneToOneAnswer",
    "event" : "update",
    "eventName" : "update OneToOneAnswer"
  },
  {
    "typeId" : "event",
    "id" : "oneToOneAnswer>delete",
    "tid": "oneToOneAnswer",
    "event" : "delete",
    "eventName" : "delete OneToOneAnswer"
  },
  {
    "typeId" : "event",
    "id" : "productQuestion>create",
    "tid": "productQuestion",
    "event" : "create",
    "eventName" : "Create ProductQuestion"
  },
  {
    "typeId" : "event",
    "id" : "productQuestion>update",
    "tid": "productQuestion",
    "event" : "update",
    "eventName" : "update ProductQuestion"
  },
  {
    "typeId" : "event",
    "id" : "productQuestion>delete",
    "tid": "productQuestion",
    "event" : "delete",
    "eventName" : "delete ProductQuestion"
  },
  {
    "typeId" : "event",
    "id" : "productAnswer>create",
    "tid": "productAnswer",
    "event" : "create",
    "eventName" : "Create ProductAnswer"
  },
  {
    "typeId" : "event",
    "id" : "productAnswer>update",
    "tid": "productAnswer",
    "event" : "update",
    "eventName" : "update ProductAnswer"
  },
  {
    "typeId" : "event",
    "id" : "productAnswer>delete",
    "tid": "productAnswer",
    "event" : "delete",
    "eventName" : "delete CommonNotice"
  },
  {
    "typeId" : "event",
    "id" : "commonNotice>create",
    "tid": "commonNotice",
    "event" : "create",
    "eventName" : "Create CommonNotice"
  },
  {
    "typeId" : "event",
    "id" : "commonNotice>update",
    "tid": "commonNotice",
    "event" : "update",
    "eventName" : "update CommonNotice"
  },
  {
    "typeId" : "event",
    "id" : "commonNotice>delete",
    "tid": "commonNotice",
    "event" : "delete",
    "eventName" : "delete CommonNotice"
  }
]